<?xml version="1.0" encoding="utf-8" standalone="yes" ?>
<T3locallang>
	<meta type="array">
		<type>database</type>
		<description>Language labels for database tables/fields belonging to extension 'mediaoembed'</description>
	</meta>
	<data type="array">
		<languageKey index="default" type="array">
			<label index="label-direct_link">direct link</label>
		</languageKey>
		<languageKey index="de" type="array">
			<label index="label-direct_link">Direktlink</label>
		</languageKey>
	</data>
</T3locallang>

